{
	"data": [
		{
			"date": "30/04/2022 17:20:32",
			"data_coin": {
				"id": "19822",
				"name": "SmartFi",
				"symbol": "SMTF",
				"blockchain": "BNB",
				"ativo": true,
				"link": "/currencies/smartfi/",
				"date": "27/04/2022 20:56:31"
			},
			"data_coinmarketcap": {
				"id": "19822",
				"price": "$2.38",
				"variation": "7.48%",
				"variation_is_up": false,
				"rank": "#6370",
				"watchlists": "129",
				"marketcap": "- -",
				"fully_diluted_marketcap": "$2,384,210,674",
				"volume_24": "$3,509",
				"volume_marketcap_24": "--",
				"max_supply": "1,000,000,000",
				"total_supply": "16,894,524",
				"contract": "0x11fD9ED04f1Eb43eF9df6425a6990609F2468895",
				"twitter": "smartfiportal",
				"telegram": "CoinMarketCapAnnouncements"
			},
			"data_twitter": {
				"data": {
					"followers_count": 1143,
					"following_count": 331,
					"tweet_count": 755,
					"listed_count": 14
				}
			},
			"data_telegram": {
				"data": 906461
			}
		},
		{
			"date": "30/04/2022 18:20:47",
			"data_coin": {
				"id": "19822",
				"name": "SmartFi",
				"symbol": "SMTF",
				"blockchain": "BNB",
				"ativo": true,
				"link": "/currencies/smartfi/",
				"date": "27/04/2022 20:56:31"
			},
			"data_coinmarketcap": {
				"id": "19822",
				"price": "$2.45",
				"variation": "4.89%",
				"variation_is_up": false,
				"rank": "#6346",
				"watchlists": "130",
				"marketcap": "- -",
				"fully_diluted_marketcap": "$2,451,370,640",
				"volume_24": "$3,611",
				"volume_marketcap_24": "--",
				"max_supply": "1,000,000,000",
				"total_supply": "16,894,524",
				"contract": "0x11fD9ED04f1Eb43eF9df6425a6990609F2468895",
				"twitter": "smartfiportal",
				"telegram": "CoinMarketCapAnnouncements"
			},
			"data_twitter": {
				"data": {
					"followers_count": 1143,
					"following_count": 331,
					"tweet_count": 755,
					"listed_count": 14
				}
			},
			"data_telegram": {
				"data": 906410
			}
		},
		{
			"date": "30/04/2022 19:21:04",
			"data_coin": {
				"id": "19822",
				"name": "SmartFi",
				"symbol": "SMTF",
				"blockchain": "BNB",
				"ativo": true,
				"link": "/currencies/smartfi/",
				"date": "27/04/2022 20:56:31"
			},
			"data_coinmarketcap": {
				"id": "19822",
				"price": "$2.47",
				"variation": "4.04%",
				"variation_is_up": true,
				"rank": "#6381",
				"watchlists": "130",
				"marketcap": "- -",
				"fully_diluted_marketcap": "$2,472,290,302",
				"volume_24": "$3,437",
				"volume_marketcap_24": "--",
				"max_supply": "1,000,000,000",
				"total_supply": "16,894,524",
				"contract": "0x11fD9ED04f1Eb43eF9df6425a6990609F2468895",
				"twitter": "smartfiportal",
				"telegram": "CoinMarketCapAnnouncements"
			},
			"data_twitter": {
				"data": {
					"followers_count": 1143,
					"following_count": 331,
					"tweet_count": 755,
					"listed_count": 14
				}
			},
			"data_telegram": {
				"data": 906346
			}
		},
		{
			"date": "30/04/2022 20:21:24",
			"data_coin": {
				"id": "19822",
				"name": "SmartFi",
				"symbol": "SMTF",
				"blockchain": "BNB",
				"ativo": true,
				"link": "/currencies/smartfi/",
				"date": "27/04/2022 20:56:31"
			},
			"data_coinmarketcap": {
				"id": "19822",
				"price": "$2.47",
				"variation": "4.01%",
				"variation_is_up": true,
				"rank": "#6386",
				"watchlists": "129",
				"marketcap": "- -",
				"fully_diluted_marketcap": "$2,472,311,631",
				"volume_24": "$3,437",
				"volume_marketcap_24": "--",
				"max_supply": "1,000,000,000",
				"total_supply": "16,894,524",
				"contract": "0x11fD9ED04f1Eb43eF9df6425a6990609F2468895",
				"twitter": "smartfiportal",
				"telegram": "CoinMarketCapAnnouncements"
			},
			"data_twitter": {
				"data": {
					"followers_count": 1143,
					"following_count": 331,
					"tweet_count": 755,
					"listed_count": 14
				}
			},
			"data_telegram": {
				"data": 906291
			}
		}
	]
}