{
	"data": [
		{
			"date": "30/04/2022 17:20:54",
			"data_coin": {
				"id": "19807",
				"name": "Uncharted",
				"symbol": "UNC",
				"blockchain": "BNB",
				"ativo": true,
				"link": "/currencies/uncharted/",
				"date": "27/04/2022 20:56:31"
			},
			"data_coinmarketcap": {
				"id": "19807",
				"price": "$0.07799",
				"variation": "3.28%",
				"variation_is_up": false,
				"rank": "#5640",
				"watchlists": "99",
				"marketcap": "$779,897",
				"fully_diluted_marketcap": "$77,989,730",
				"volume_24": "$11,626",
				"volume_marketcap_24": "0.01491",
				"max_supply": "1,000,000,000",
				"total_supply": "1,000,000,000",
				"contract": "0x77C54B5f495016CCDbC20A52a9D3F421aF21B04D",
				"telegram": "UnchartedUNC",
				"twitter": "unchartedUNC"
			},
			"data_twitter": {
				"data": {
					"followers_count": 81016,
					"following_count": 36,
					"tweet_count": 75,
					"listed_count": 1
				}
			},
			"data_telegram": {
				"data": 54243
			}
		},
		{
			"date": "30/04/2022 18:21:10",
			"data_coin": {
				"id": "19807",
				"name": "Uncharted",
				"symbol": "UNC",
				"blockchain": "BNB",
				"ativo": true,
				"link": "/currencies/uncharted/",
				"date": "27/04/2022 20:56:31"
			},
			"data_coinmarketcap": {
				"id": "19807",
				"price": "$0.07791",
				"variation": "3.19%",
				"variation_is_up": false,
				"rank": "#5629",
				"watchlists": "99",
				"marketcap": "$779,143",
				"fully_diluted_marketcap": "$77,914,302",
				"volume_24": "$11,632",
				"volume_marketcap_24": "0.01493",
				"max_supply": "1,000,000,000",
				"total_supply": "1,000,000,000",
				"contract": "0x77C54B5f495016CCDbC20A52a9D3F421aF21B04D",
				"telegram": "UnchartedUNC",
				"twitter": "unchartedUNC"
			},
			"data_twitter": {
				"data": {
					"followers_count": 81021,
					"following_count": 36,
					"tweet_count": 75,
					"listed_count": 1
				}
			},
			"data_telegram": {
				"data": 54233
			}
		},
		{
			"date": "30/04/2022 19:21:26",
			"data_coin": {
				"id": "19807",
				"name": "Uncharted",
				"symbol": "UNC",
				"blockchain": "BNB",
				"ativo": true,
				"link": "/currencies/uncharted/",
				"date": "27/04/2022 20:56:31"
			},
			"data_coinmarketcap": {
				"id": "19807",
				"price": "$0.07786",
				"variation": "3.25%",
				"variation_is_up": false,
				"rank": "#5641",
				"watchlists": "99",
				"marketcap": "$778,607",
				"fully_diluted_marketcap": "$77,860,670",
				"volume_24": "$11,726",
				"volume_marketcap_24": "0.01506",
				"max_supply": "1,000,000,000",
				"total_supply": "1,000,000,000",
				"contract": "0x77C54B5f495016CCDbC20A52a9D3F421aF21B04D",
				"telegram": "UnchartedUNC",
				"twitter": "unchartedUNC"
			},
			"data_twitter": {
				"data": {
					"followers_count": 81036,
					"following_count": 36,
					"tweet_count": 75,
					"listed_count": 1
				}
			},
			"data_telegram": {
				"data": 54228
			}
		},
		{
			"date": "30/04/2022 20:21:47",
			"data_coin": {
				"id": "19807",
				"name": "Uncharted",
				"symbol": "UNC",
				"blockchain": "BNB",
				"ativo": true,
				"link": "/currencies/uncharted/",
				"date": "27/04/2022 20:56:31"
			},
			"data_coinmarketcap": {
				"id": "19807",
				"price": "$0.07773",
				"variation": "3.12%",
				"variation_is_up": false,
				"rank": "#5645",
				"watchlists": "98",
				"marketcap": "$777,335",
				"fully_diluted_marketcap": "$77,733,493",
				"volume_24": "$11,886",
				"volume_marketcap_24": "0.01529",
				"max_supply": "1,000,000,000",
				"total_supply": "1,000,000,000",
				"contract": "0x77C54B5f495016CCDbC20A52a9D3F421aF21B04D",
				"telegram": "UnchartedUNC",
				"twitter": "unchartedUNC"
			},
			"data_twitter": {
				"data": {
					"followers_count": 81044,
					"following_count": 36,
					"tweet_count": 75,
					"listed_count": 1
				}
			},
			"data_telegram": {
				"data": 54223
			}
		},
		{
			"date": "30/04/2022 21:22:10",
			"data_coin": {
				"id": "19807",
				"name": "Uncharted",
				"symbol": "UNC",
				"blockchain": "BNB",
				"ativo": true,
				"link": "/currencies/uncharted/",
				"date": "27/04/2022 20:56:31"
			},
			"data_coinmarketcap": {
				"id": "19807",
				"price": "$0.07752",
				"variation": "3.38%",
				"variation_is_up": false,
				"rank": "#6232",
				"watchlists": "98",
				"marketcap": "$775,195",
				"fully_diluted_marketcap": "$77,519,501",
				"volume_24": "$2,981",
				"volume_marketcap_24": "0.003845",
				"max_supply": "1,000,000,000",
				"total_supply": "1,000,000,000",
				"contract": "0x77C54B5f495016CCDbC20A52a9D3F421aF21B04D",
				"telegram": "UnchartedUNC",
				"twitter": "unchartedUNC"
			},
			"data_twitter": {
				"data": {
					"followers_count": 81052,
					"following_count": 36,
					"tweet_count": 75,
					"listed_count": 1
				}
			},
			"data_telegram": {
				"data": 54219
			}
		},
		{
			"date": "30/04/2022 21:23:27",
			"data_coin": {
				"id": "19807",
				"name": "Uncharted",
				"symbol": "UNC",
				"blockchain": "BNB",
				"ativo": true,
				"link": "/currencies/uncharted/",
				"date": "27/04/2022 20:56:31"
			},
			"data_coinmarketcap": {
				"id": "19807",
				"price": "$0.07752",
				"variation": "3.38%",
				"variation_is_up": false,
				"rank": "#6232",
				"watchlists": "98",
				"marketcap": "$775,195",
				"fully_diluted_marketcap": "$77,519,501",
				"volume_24": "$2,981",
				"volume_marketcap_24": "0.003845",
				"max_supply": "1,000,000,000",
				"total_supply": "1,000,000,000",
				"contract": "0x77C54B5f495016CCDbC20A52a9D3F421aF21B04D",
				"telegram": "UnchartedUNC",
				"twitter": "unchartedUNC"
			},
			"data_twitter": {
				"data": {
					"followers_count": 81052,
					"following_count": 36,
					"tweet_count": 75,
					"listed_count": 1
				}
			},
			"data_telegram": {
				"data": 54219
			}
		},
		{
			"date": "30/04/2022 21:27:59",
			"data_coin": {
				"id": "19807",
				"name": "Uncharted",
				"symbol": "UNC",
				"blockchain": "BNB",
				"ativo": true,
				"link": "/currencies/uncharted/",
				"date": "27/04/2022 20:56:31"
			},
			"data_coinmarketcap": {
				"id": "19807",
				"price": "$0.07752",
				"variation": "3.38%",
				"variation_is_up": false,
				"rank": "#6232",
				"watchlists": "98",
				"marketcap": "$775,195",
				"fully_diluted_marketcap": "$77,519,501",
				"volume_24": "$2,981",
				"volume_marketcap_24": "0.003845",
				"max_supply": "1,000,000,000",
				"total_supply": "1,000,000,000",
				"contract": "0x77C54B5f495016CCDbC20A52a9D3F421aF21B04D",
				"telegram": "UnchartedUNC",
				"twitter": "unchartedUNC"
			},
			"data_twitter": {
				"data": {
					"followers_count": 81052,
					"following_count": 36,
					"tweet_count": 75,
					"listed_count": 1
				}
			},
			"data_telegram": {
				"data": 54219
			}
		},
		{
			"date": "30/04/2022 21:31:29",
			"data_coin": {
				"id": "19807",
				"name": "Uncharted",
				"symbol": "UNC",
				"blockchain": "BNB",
				"ativo": true,
				"link": "/currencies/uncharted/",
				"date": "27/04/2022 20:56:31",
				"dadosTwitter_1": {
					"data": {
						"followers_count": 81052,
						"following_count": 36,
						"tweet_count": 75,
						"listed_count": 1
					}
				},
				"dadosTelegram_1": {
					"data": 54219
				}
			},
			"data_coinmarketcap": {
				"id": "19807",
				"price": "$0.07752",
				"variation": "3.38%",
				"variation_is_up": false,
				"rank": "#6234",
				"watchlists": "98",
				"marketcap": "$775,202",
				"fully_diluted_marketcap": "$77,520,196",
				"volume_24": "$2,990",
				"volume_marketcap_24": "0.003857",
				"max_supply": "1,000,000,000",
				"total_supply": "1,000,000,000",
				"contract": "0x77C54B5f495016CCDbC20A52a9D3F421aF21B04D",
				"telegram": "UnchartedUNC",
				"twitter": "unchartedUNC"
			},
			"data_twitter": {
				"data": {
					"followers_count": 81052,
					"following_count": 36,
					"tweet_count": 75,
					"listed_count": 1
				}
			},
			"data_telegram": {
				"data": 54220
			}
		},
		{
			"date": "30/04/2022 22:31:53",
			"data_coin": {
				"id": "19807",
				"name": "Uncharted",
				"symbol": "UNC",
				"blockchain": "BNB",
				"ativo": true,
				"link": "/currencies/uncharted/",
				"date": "27/04/2022 20:56:31",
				"dadosTwitter_1": {
					"data": {
						"followers_count": 81052,
						"following_count": 36,
						"tweet_count": 75,
						"listed_count": 1
					}
				},
				"dadosTelegram_1": {
					"data": 54219
				},
				"infoCoinMarketCap_1": {
					"id": "19807",
					"price": "$0.07752",
					"variation": "3.38%",
					"variation_is_up": false,
					"rank": "#6232",
					"watchlists": "98",
					"marketcap": "$775,195",
					"fully_diluted_marketcap": "$77,519,501",
					"volume_24": "$2,981",
					"volume_marketcap_24": "0.003845",
					"max_supply": "1,000,000,000",
					"total_supply": "1,000,000,000",
					"contract": "0x77C54B5f495016CCDbC20A52a9D3F421aF21B04D",
					"telegram": "UnchartedUNC",
					"twitter": "unchartedUNC"
				}
			},
			"data_coinmarketcap": {
				"id": "19807",
				"price": "$0.07729",
				"variation": "3.38%",
				"variation_is_up": false,
				"rank": "#6175",
				"watchlists": "98",
				"marketcap": "$772,932",
				"fully_diluted_marketcap": "$77,293,154",
				"volume_24": "$3,324",
				"volume_marketcap_24": "0.0043",
				"max_supply": "1,000,000,000",
				"total_supply": "1,000,000,000",
				"contract": "0x77C54B5f495016CCDbC20A52a9D3F421aF21B04D",
				"telegram": "UnchartedUNC",
				"twitter": "unchartedUNC"
			},
			"data_twitter": {
				"data": {
					"followers_count": 81066,
					"following_count": 36,
					"tweet_count": 75,
					"listed_count": 1
				}
			},
			"data_telegram": {
				"data": 54218
			}
		},
		{
			"date": "30/04/2022 23:32:10",
			"data_coin": {
				"id": "19807",
				"name": "Uncharted",
				"symbol": "UNC",
				"blockchain": "BNB",
				"ativo": true,
				"link": "/currencies/uncharted/",
				"date": "27/04/2022 20:56:31",
				"dadosTwitter_1": {
					"data": {
						"followers_count": 81052,
						"following_count": 36,
						"tweet_count": 75,
						"listed_count": 1
					}
				},
				"dadosTelegram_1": {
					"data": 54220
				},
				"infoCoinMarketCap_1": {
					"id": "19807",
					"price": "$0.07752",
					"variation": "3.38%",
					"variation_is_up": false,
					"rank": "#6234",
					"watchlists": "98",
					"marketcap": "$775,202",
					"fully_diluted_marketcap": "$77,520,196",
					"volume_24": "$2,990",
					"volume_marketcap_24": "0.003857",
					"max_supply": "1,000,000,000",
					"total_supply": "1,000,000,000",
					"contract": "0x77C54B5f495016CCDbC20A52a9D3F421aF21B04D",
					"telegram": "UnchartedUNC",
					"twitter": "unchartedUNC"
				}
			},
			"data_coinmarketcap": {
				"id": "19807",
				"price": "$0.07729",
				"variation": "3.28%",
				"variation_is_up": false,
				"rank": "#6186",
				"watchlists": "98",
				"marketcap": "$772,950",
				"fully_diluted_marketcap": "$77,294,964",
				"volume_24": "$3,342",
				"volume_marketcap_24": "0.004323",
				"max_supply": "1,000,000,000",
				"total_supply": "1,000,000,000",
				"contract": "0x77C54B5f495016CCDbC20A52a9D3F421aF21B04D",
				"telegram": "UnchartedUNC",
				"twitter": "unchartedUNC"
			},
			"data_twitter": {
				"data": {
					"followers_count": 81071,
					"following_count": 36,
					"tweet_count": 75,
					"listed_count": 1
				}
			},
			"data_telegram": {
				"data": 54215
			}
		},
		{
			"date": "01/05/2022 00:32:30",
			"data_coin": {
				"id": "19807",
				"name": "Uncharted",
				"symbol": "UNC",
				"blockchain": "BNB",
				"ativo": true,
				"link": "/currencies/uncharted/",
				"date": "27/04/2022 20:56:31",
				"dadosTwitter_1": {
					"data": {
						"followers_count": 81066,
						"following_count": 36,
						"tweet_count": 75,
						"listed_count": 1
					}
				},
				"dadosTelegram_1": {
					"data": 54218
				},
				"infoCoinMarketCap_1": {
					"id": "19807",
					"price": "$0.07729",
					"variation": "3.38%",
					"variation_is_up": false,
					"rank": "#6175",
					"watchlists": "98",
					"marketcap": "$772,932",
					"fully_diluted_marketcap": "$77,293,154",
					"volume_24": "$3,324",
					"volume_marketcap_24": "0.0043",
					"max_supply": "1,000,000,000",
					"total_supply": "1,000,000,000",
					"contract": "0x77C54B5f495016CCDbC20A52a9D3F421aF21B04D",
					"telegram": "UnchartedUNC",
					"twitter": "unchartedUNC"
				}
			},
			"data_coinmarketcap": {
				"id": "19807",
				"price": "$0.077",
				"variation": "3.63%",
				"variation_is_up": false,
				"rank": "#6122",
				"watchlists": "98",
				"marketcap": "$769,964",
				"fully_diluted_marketcap": "$76,996,416",
				"volume_24": "$3,833",
				"volume_marketcap_24": "0.004978",
				"max_supply": "1,000,000,000",
				"total_supply": "1,000,000,000",
				"contract": "0x77C54B5f495016CCDbC20A52a9D3F421aF21B04D",
				"telegram": "UnchartedUNC",
				"twitter": "unchartedUNC"
			},
			"data_twitter": {
				"data": {
					"followers_count": 81022,
					"following_count": 36,
					"tweet_count": 75,
					"listed_count": 1
				}
			},
			"data_telegram": {
				"data": 54210
			}
		},
		{
			"date": "01/05/2022 01:32:56",
			"data_coin": {
				"id": "19807",
				"name": "Uncharted",
				"symbol": "UNC",
				"blockchain": "BNB",
				"ativo": true,
				"link": "/currencies/uncharted/",
				"date": "27/04/2022 20:56:31",
				"dadosTwitter_1": {
					"data": {
						"followers_count": 81071,
						"following_count": 36,
						"tweet_count": 75,
						"listed_count": 1
					}
				},
				"dadosTelegram_1": {
					"data": 54215
				},
				"infoCoinMarketCap_1": {
					"id": "19807",
					"price": "$0.07729",
					"variation": "3.28%",
					"variation_is_up": false,
					"rank": "#6186",
					"watchlists": "98",
					"marketcap": "$772,950",
					"fully_diluted_marketcap": "$77,294,964",
					"volume_24": "$3,342",
					"volume_marketcap_24": "0.004323",
					"max_supply": "1,000,000,000",
					"total_supply": "1,000,000,000",
					"contract": "0x77C54B5f495016CCDbC20A52a9D3F421aF21B04D",
					"telegram": "UnchartedUNC",
					"twitter": "unchartedUNC"
				}
			},
			"data_coinmarketcap": {
				"id": "19807",
				"price": "$0.077",
				"variation": "3.56%",
				"variation_is_up": false,
				"rank": "#6130",
				"watchlists": "98",
				"marketcap": "$769,984",
				"fully_diluted_marketcap": "$76,998,408",
				"volume_24": "$3,833",
				"volume_marketcap_24": "0.004978",
				"max_supply": "1,000,000,000",
				"total_supply": "1,000,000,000",
				"contract": "0x77C54B5f495016CCDbC20A52a9D3F421aF21B04D",
				"telegram": "UnchartedUNC",
				"twitter": "unchartedUNC"
			},
			"data_twitter": {
				"data": {
					"followers_count": 81030,
					"following_count": 36,
					"tweet_count": 75,
					"listed_count": 1
				}
			},
			"data_telegram": {
				"data": 54202
			}
		},
		{
			"date": "01/05/2022 02:33:14",
			"data_coin": {
				"id": "19807",
				"name": "Uncharted",
				"symbol": "UNC",
				"blockchain": "BNB",
				"ativo": true,
				"link": "/currencies/uncharted/",
				"date": "27/04/2022 20:56:31",
				"dadosTwitter_1": {
					"data": {
						"followers_count": 81022,
						"following_count": 36,
						"tweet_count": 75,
						"listed_count": 1
					}
				},
				"dadosTelegram_1": {
					"data": 54210
				},
				"infoCoinMarketCap_1": {
					"id": "19807",
					"price": "$0.077",
					"variation": "3.63%",
					"variation_is_up": false,
					"rank": "#6122",
					"watchlists": "98",
					"marketcap": "$769,964",
					"fully_diluted_marketcap": "$76,996,416",
					"volume_24": "$3,833",
					"volume_marketcap_24": "0.004978",
					"max_supply": "1,000,000,000",
					"total_supply": "1,000,000,000",
					"contract": "0x77C54B5f495016CCDbC20A52a9D3F421aF21B04D",
					"telegram": "UnchartedUNC",
					"twitter": "unchartedUNC"
				}
			},
			"data_coinmarketcap": {
				"id": "19807",
				"price": "$0.07686",
				"variation": "3.11%",
				"variation_is_up": false,
				"rank": "#6148",
				"watchlists": "98",
				"marketcap": "$768,649",
				"fully_diluted_marketcap": "$76,864,872",
				"volume_24": "$3,834",
				"volume_marketcap_24": "0.004988",
				"max_supply": "1,000,000,000",
				"total_supply": "1,000,000,000",
				"contract": "0x77C54B5f495016CCDbC20A52a9D3F421aF21B04D",
				"telegram": "UnchartedUNC",
				"twitter": "unchartedUNC"
			},
			"data_twitter": {
				"data": {
					"followers_count": 81062,
					"following_count": 36,
					"tweet_count": 75,
					"listed_count": 1
				}
			},
			"data_telegram": {
				"data": 54191
			}
		},
		{
			"date": "01/05/2022 03:33:34",
			"data_coin": {
				"id": "19807",
				"name": "Uncharted",
				"symbol": "UNC",
				"blockchain": "BNB",
				"ativo": true,
				"link": "/currencies/uncharted/",
				"date": "27/04/2022 20:56:31",
				"dadosTwitter_1": {
					"data": {
						"followers_count": 81030,
						"following_count": 36,
						"tweet_count": 75,
						"listed_count": 1
					}
				},
				"dadosTelegram_1": {
					"data": 54202
				},
				"infoCoinMarketCap_1": {
					"id": "19807",
					"price": "$0.077",
					"variation": "3.56%",
					"variation_is_up": false,
					"rank": "#6130",
					"watchlists": "98",
					"marketcap": "$769,984",
					"fully_diluted_marketcap": "$76,998,408",
					"volume_24": "$3,833",
					"volume_marketcap_24": "0.004978",
					"max_supply": "1,000,000,000",
					"total_supply": "1,000,000,000",
					"contract": "0x77C54B5f495016CCDbC20A52a9D3F421aF21B04D",
					"telegram": "UnchartedUNC",
					"twitter": "unchartedUNC"
				}
			},
			"data_coinmarketcap": {
				"id": "19807",
				"price": "$0.07686",
				"variation": "3.12%",
				"variation_is_up": false,
				"rank": "#6155",
				"watchlists": "98",
				"marketcap": "$768,633",
				"fully_diluted_marketcap": "$76,863,255",
				"volume_24": "$3,847",
				"volume_marketcap_24": "0.005006",
				"max_supply": "1,000,000,000",
				"total_supply": "1,000,000,000",
				"contract": "0x77C54B5f495016CCDbC20A52a9D3F421aF21B04D",
				"telegram": "UnchartedUNC",
				"twitter": "unchartedUNC"
			},
			"data_twitter": {
				"data": {
					"followers_count": 81070,
					"following_count": 36,
					"tweet_count": 75,
					"listed_count": 1
				}
			},
			"data_telegram": {
				"data": 54185
			}
		},
		{
			"date": "01/05/2022 04:34:17",
			"data_coin": {
				"id": "19807",
				"name": "Uncharted",
				"symbol": "UNC",
				"blockchain": "BNB",
				"ativo": true,
				"link": "/currencies/uncharted/",
				"date": "27/04/2022 20:56:31",
				"dadosTwitter_1": {
					"data": {
						"followers_count": 81062,
						"following_count": 36,
						"tweet_count": 75,
						"listed_count": 1
					}
				},
				"dadosTelegram_1": {
					"data": 54191
				},
				"infoCoinMarketCap_1": {
					"id": "19807",
					"price": "$0.07686",
					"variation": "3.11%",
					"variation_is_up": false,
					"rank": "#6148",
					"watchlists": "98",
					"marketcap": "$768,649",
					"fully_diluted_marketcap": "$76,864,872",
					"volume_24": "$3,834",
					"volume_marketcap_24": "0.004988",
					"max_supply": "1,000,000,000",
					"total_supply": "1,000,000,000",
					"contract": "0x77C54B5f495016CCDbC20A52a9D3F421aF21B04D",
					"telegram": "UnchartedUNC",
					"twitter": "unchartedUNC"
				}
			},
			"data_coinmarketcap": {
				"id": "19807",
				"price": "$0.07685",
				"variation": "2.91%",
				"variation_is_up": false,
				"rank": "#6159",
				"watchlists": "98",
				"marketcap": "$768,538",
				"fully_diluted_marketcap": "$76,853,768",
				"volume_24": "$3,837",
				"volume_marketcap_24": "0.004993",
				"max_supply": "1,000,000,000",
				"total_supply": "1,000,000,000",
				"contract": "0x77C54B5f495016CCDbC20A52a9D3F421aF21B04D",
				"telegram": "UnchartedUNC",
				"twitter": "unchartedUNC"
			},
			"data_twitter": {
				"data": {
					"followers_count": 81094,
					"following_count": 36,
					"tweet_count": 75,
					"listed_count": 1
				}
			},
			"data_telegram": {
				"data": 54180
			}
		},
		{
			"date": "01/05/2022 05:35:10",
			"data_coin": {
				"id": "19807",
				"name": "Uncharted",
				"symbol": "UNC",
				"blockchain": "BNB",
				"ativo": true,
				"link": "/currencies/uncharted/",
				"date": "27/04/2022 20:56:31",
				"dadosTwitter_1": {
					"data": {
						"followers_count": 81062,
						"following_count": 36,
						"tweet_count": 75,
						"listed_count": 1
					}
				},
				"dadosTelegram_1": {
					"data": 54191
				},
				"infoCoinMarketCap_1": {
					"id": "19807",
					"price": "$0.07686",
					"variation": "3.11%",
					"variation_is_up": false,
					"rank": "#6148",
					"watchlists": "98",
					"marketcap": "$768,649",
					"fully_diluted_marketcap": "$76,864,872",
					"volume_24": "$3,834",
					"volume_marketcap_24": "0.004988",
					"max_supply": "1,000,000,000",
					"total_supply": "1,000,000,000",
					"contract": "0x77C54B5f495016CCDbC20A52a9D3F421aF21B04D",
					"telegram": "UnchartedUNC",
					"twitter": "unchartedUNC"
				}
			},
			"data_coinmarketcap": {
				"id": "19807",
				"price": "$0.07685",
				"variation": "3.34%",
				"variation_is_up": false,
				"rank": "#6162",
				"watchlists": "98",
				"marketcap": "$768,504",
				"fully_diluted_marketcap": "$76,850,431",
				"volume_24": "$3,855",
				"volume_marketcap_24": "0.005017",
				"max_supply": "1,000,000,000",
				"total_supply": "1,000,000,000",
				"contract": "0x77C54B5f495016CCDbC20A52a9D3F421aF21B04D",
				"telegram": "UnchartedUNC",
				"twitter": "unchartedUNC"
			},
			"data_twitter": {
				"data": {
					"followers_count": 81105,
					"following_count": 36,
					"tweet_count": 75,
					"listed_count": 1
				}
			},
			"data_telegram": {
				"data": 54176
			}
		},
		{
			"date": "01/05/2022 06:36:05",
			"data_coin": {
				"id": "19807",
				"name": "Uncharted",
				"symbol": "UNC",
				"blockchain": "BNB",
				"ativo": true,
				"link": "/currencies/uncharted/",
				"date": "27/04/2022 20:56:31",
				"dadosTwitter_1": {
					"data": {
						"followers_count": 81062,
						"following_count": 36,
						"tweet_count": 75,
						"listed_count": 1
					}
				},
				"dadosTelegram_1": {
					"data": 54191
				},
				"infoCoinMarketCap_1": {
					"id": "19807",
					"price": "$0.07686",
					"variation": "3.11%",
					"variation_is_up": false,
					"rank": "#6148",
					"watchlists": "98",
					"marketcap": "$768,649",
					"fully_diluted_marketcap": "$76,864,872",
					"volume_24": "$3,834",
					"volume_marketcap_24": "0.004988",
					"max_supply": "1,000,000,000",
					"total_supply": "1,000,000,000",
					"contract": "0x77C54B5f495016CCDbC20A52a9D3F421aF21B04D",
					"telegram": "UnchartedUNC",
					"twitter": "unchartedUNC"
				}
			},
			"data_coinmarketcap": {
				"id": "19807",
				"price": "$0.0767",
				"variation": "3.52%",
				"variation_is_up": false,
				"rank": "#6140",
				"watchlists": "98",
				"marketcap": "$767,031",
				"fully_diluted_marketcap": "$76,703,129",
				"volume_24": "$4,048",
				"volume_marketcap_24": "0.005278",
				"max_supply": "1,000,000,000",
				"total_supply": "1,000,000,000",
				"contract": "0x77C54B5f495016CCDbC20A52a9D3F421aF21B04D",
				"telegram": "UnchartedUNC",
				"twitter": "unchartedUNC"
			},
			"data_twitter": {
				"data": {
					"followers_count": 81119,
					"following_count": 36,
					"tweet_count": 75,
					"listed_count": 1
				}
			},
			"data_telegram": {
				"data": 54171
			}
		},
		{
			"date": "01/05/2022 07:36:51",
			"data_coin": {
				"id": "19807",
				"name": "Uncharted",
				"symbol": "UNC",
				"blockchain": "BNB",
				"ativo": true,
				"link": "/currencies/uncharted/",
				"date": "27/04/2022 20:56:31",
				"dadosTwitter_1": {
					"data": {
						"followers_count": 81062,
						"following_count": 36,
						"tweet_count": 75,
						"listed_count": 1
					}
				},
				"dadosTelegram_1": {
					"data": 54191
				},
				"infoCoinMarketCap_1": {
					"id": "19807",
					"price": "$0.07686",
					"variation": "3.11%",
					"variation_is_up": false,
					"rank": "#6148",
					"watchlists": "98",
					"marketcap": "$768,649",
					"fully_diluted_marketcap": "$76,864,872",
					"volume_24": "$3,834",
					"volume_marketcap_24": "0.004988",
					"max_supply": "1,000,000,000",
					"total_supply": "1,000,000,000",
					"contract": "0x77C54B5f495016CCDbC20A52a9D3F421aF21B04D",
					"telegram": "UnchartedUNC",
					"twitter": "unchartedUNC"
				}
			},
			"data_coinmarketcap": {
				"id": "19807",
				"price": "$0.0767",
				"variation": "3.42%",
				"variation_is_up": false,
				"rank": "#6146",
				"watchlists": "98",
				"marketcap": "$767,014",
				"fully_diluted_marketcap": "$76,701,391",
				"volume_24": "$4,044",
				"volume_marketcap_24": "0.005273",
				"max_supply": "1,000,000,000",
				"total_supply": "1,000,000,000",
				"contract": "0x77C54B5f495016CCDbC20A52a9D3F421aF21B04D",
				"telegram": "UnchartedUNC",
				"twitter": "unchartedUNC"
			},
			"data_twitter": {
				"data": {
					"followers_count": 81125,
					"following_count": 36,
					"tweet_count": 75,
					"listed_count": 1
				}
			},
			"data_telegram": {
				"data": 54161
			}
		},
		{
			"date": "01/05/2022 08:37:40",
			"data_coin": {
				"id": "19807",
				"name": "Uncharted",
				"symbol": "UNC",
				"blockchain": "BNB",
				"ativo": true,
				"link": "/currencies/uncharted/",
				"date": "27/04/2022 20:56:31",
				"dadosTwitter_1": {
					"data": {
						"followers_count": 81062,
						"following_count": 36,
						"tweet_count": 75,
						"listed_count": 1
					}
				},
				"dadosTelegram_1": {
					"data": 54191
				},
				"infoCoinMarketCap_1": {
					"id": "19807",
					"price": "$0.07686",
					"variation": "3.11%",
					"variation_is_up": false,
					"rank": "#6148",
					"watchlists": "98",
					"marketcap": "$768,649",
					"fully_diluted_marketcap": "$76,864,872",
					"volume_24": "$3,834",
					"volume_marketcap_24": "0.004988",
					"max_supply": "1,000,000,000",
					"total_supply": "1,000,000,000",
					"contract": "0x77C54B5f495016CCDbC20A52a9D3F421aF21B04D",
					"telegram": "UnchartedUNC",
					"twitter": "unchartedUNC"
				}
			},
			"data_coinmarketcap": {
				"id": "19807",
				"price": "$0.07709",
				"variation": "2.20%",
				"variation_is_up": false,
				"rank": "#6152",
				"watchlists": "99",
				"marketcap": "$770,876",
				"fully_diluted_marketcap": "$77,087,557",
				"volume_24": "$4,041",
				"volume_marketcap_24": "0.005243",
				"max_supply": "1,000,000,000",
				"total_supply": "1,000,000,000",
				"contract": "0x77C54B5f495016CCDbC20A52a9D3F421aF21B04D",
				"telegram": "UnchartedUNC",
				"twitter": "unchartedUNC"
			},
			"data_twitter": {
				"data": {
					"followers_count": 81138,
					"following_count": 36,
					"tweet_count": 75,
					"listed_count": 1
				}
			},
			"data_telegram": {
				"data": 54155
			}
		},
		{
			"date": "01/05/2022 09:38:20",
			"data_coin": {
				"id": "19807",
				"name": "Uncharted",
				"symbol": "UNC",
				"blockchain": "BNB",
				"ativo": true,
				"link": "/currencies/uncharted/",
				"date": "27/04/2022 20:56:31",
				"dadosTwitter_1": {
					"data": {
						"followers_count": 81062,
						"following_count": 36,
						"tweet_count": 75,
						"listed_count": 1
					}
				},
				"dadosTelegram_1": {
					"data": 54191
				},
				"infoCoinMarketCap_1": {
					"id": "19807",
					"price": "$0.07686",
					"variation": "3.11%",
					"variation_is_up": false,
					"rank": "#6148",
					"watchlists": "98",
					"marketcap": "$768,649",
					"fully_diluted_marketcap": "$76,864,872",
					"volume_24": "$3,834",
					"volume_marketcap_24": "0.004988",
					"max_supply": "1,000,000,000",
					"total_supply": "1,000,000,000",
					"contract": "0x77C54B5f495016CCDbC20A52a9D3F421aF21B04D",
					"telegram": "UnchartedUNC",
					"twitter": "unchartedUNC"
				}
			},
			"data_coinmarketcap": {
				"id": "19807",
				"price": "$0.0771",
				"variation": "1.91%",
				"variation_is_up": false,
				"rank": "#6155",
				"watchlists": "99",
				"marketcap": "$770,984",
				"fully_diluted_marketcap": "$77,098,412",
				"volume_24": "$4,078",
				"volume_marketcap_24": "0.005289",
				"max_supply": "1,000,000,000",
				"total_supply": "1,000,000,000",
				"contract": "0x77C54B5f495016CCDbC20A52a9D3F421aF21B04D",
				"telegram": "UnchartedUNC",
				"twitter": "unchartedUNC"
			},
			"data_twitter": {
				"data": {
					"followers_count": 81146,
					"following_count": 36,
					"tweet_count": 75,
					"listed_count": 1
				}
			},
			"data_telegram": {
				"data": 54151
			}
		},
		{
			"date": "01/05/2022 10:39:03",
			"data_coin": {
				"id": "19807",
				"name": "Uncharted",
				"symbol": "UNC",
				"blockchain": "BNB",
				"ativo": true,
				"link": "/currencies/uncharted/",
				"date": "27/04/2022 20:56:31",
				"dadosTwitter_1": {
					"data": {
						"followers_count": 81062,
						"following_count": 36,
						"tweet_count": 75,
						"listed_count": 1
					}
				},
				"dadosTelegram_1": {
					"data": 54191
				},
				"infoCoinMarketCap_1": {
					"id": "19807",
					"price": "$0.07686",
					"variation": "3.11%",
					"variation_is_up": false,
					"rank": "#6148",
					"watchlists": "98",
					"marketcap": "$768,649",
					"fully_diluted_marketcap": "$76,864,872",
					"volume_24": "$3,834",
					"volume_marketcap_24": "0.004988",
					"max_supply": "1,000,000,000",
					"total_supply": "1,000,000,000",
					"contract": "0x77C54B5f495016CCDbC20A52a9D3F421aF21B04D",
					"telegram": "UnchartedUNC",
					"twitter": "unchartedUNC"
				}
			},
			"data_coinmarketcap": {
				"id": "19807",
				"price": "$0.07666",
				"variation": "2.34%",
				"variation_is_up": false,
				"rank": "#6146",
				"watchlists": "99",
				"marketcap": "$766,642",
				"fully_diluted_marketcap": "$76,664,235",
				"volume_24": "$4,249",
				"volume_marketcap_24": "0.005542",
				"max_supply": "1,000,000,000",
				"total_supply": "1,000,000,000",
				"contract": "0x77C54B5f495016CCDbC20A52a9D3F421aF21B04D",
				"telegram": "UnchartedUNC",
				"twitter": "unchartedUNC"
			},
			"data_twitter": {
				"data": {
					"followers_count": 81165,
					"following_count": 36,
					"tweet_count": 75,
					"listed_count": 1
				}
			},
			"data_telegram": {
				"data": 54145
			}
		},
		{
			"date": "01/05/2022 11:39:11",
			"data_coin": {
				"id": "19807",
				"name": "Uncharted",
				"symbol": "UNC",
				"blockchain": "BNB",
				"ativo": true,
				"link": "/currencies/uncharted/",
				"date": "27/04/2022 20:56:31",
				"dadosTwitter_1": {
					"data": {
						"followers_count": 81062,
						"following_count": 36,
						"tweet_count": 75,
						"listed_count": 1
					}
				},
				"dadosTelegram_1": {
					"data": 54191
				},
				"infoCoinMarketCap_1": {
					"id": "19807",
					"price": "$0.07686",
					"variation": "3.11%",
					"variation_is_up": false,
					"rank": "#6148",
					"watchlists": "98",
					"marketcap": "$768,649",
					"fully_diluted_marketcap": "$76,864,872",
					"volume_24": "$3,834",
					"volume_marketcap_24": "0.004988",
					"max_supply": "1,000,000,000",
					"total_supply": "1,000,000,000",
					"contract": "0x77C54B5f495016CCDbC20A52a9D3F421aF21B04D",
					"telegram": "UnchartedUNC",
					"twitter": "unchartedUNC"
				}
			},
			"data_coinmarketcap": {
				"id": "19807",
				"price": "$0.07653",
				"variation": "2.25%",
				"variation_is_up": false,
				"rank": "#6143",
				"watchlists": "99",
				"marketcap": "$765,338",
				"fully_diluted_marketcap": "$76,533,811",
				"volume_24": "$4,307",
				"volume_marketcap_24": "0.005628",
				"max_supply": "1,000,000,000",
				"total_supply": "1,000,000,000",
				"contract": "0x77C54B5f495016CCDbC20A52a9D3F421aF21B04D",
				"telegram": "UnchartedUNC",
				"twitter": "unchartedUNC"
			},
			"data_twitter": {
				"data": {
					"followers_count": 81171,
					"following_count": 36,
					"tweet_count": 75,
					"listed_count": 1
				}
			},
			"data_telegram": {
				"data": 54135
			}
		},
		{
			"date": "01/05/2022 12:39:46",
			"data_coin": {
				"id": "19807",
				"name": "Uncharted",
				"symbol": "UNC",
				"blockchain": "BNB",
				"ativo": true,
				"link": "/currencies/uncharted/",
				"date": "27/04/2022 20:56:31",
				"dadosTwitter_1": {
					"data": {
						"followers_count": 81165,
						"following_count": 36,
						"tweet_count": 75,
						"listed_count": 1
					}
				},
				"dadosTelegram_1": {
					"data": 54145
				},
				"infoCoinMarketCap_1": {
					"id": "19807",
					"price": "$0.07666",
					"variation": "2.34%",
					"variation_is_up": false,
					"rank": "#6146",
					"watchlists": "99",
					"marketcap": "$766,642",
					"fully_diluted_marketcap": "$76,664,235",
					"volume_24": "$4,249",
					"volume_marketcap_24": "0.005542",
					"max_supply": "1,000,000,000",
					"total_supply": "1,000,000,000",
					"contract": "0x77C54B5f495016CCDbC20A52a9D3F421aF21B04D",
					"telegram": "UnchartedUNC",
					"twitter": "unchartedUNC"
				}
			},
			"data_coinmarketcap": {
				"id": "19807",
				"price": "$0.07691",
				"variation": "1.72%",
				"variation_is_up": false,
				"rank": "#6137",
				"watchlists": "98",
				"marketcap": "$769,143",
				"fully_diluted_marketcap": "$76,914,321",
				"volume_24": "$4,330",
				"volume_marketcap_24": "0.005629",
				"max_supply": "1,000,000,000",
				"total_supply": "1,000,000,000",
				"contract": "0x77C54B5f495016CCDbC20A52a9D3F421aF21B04D",
				"telegram": "UnchartedUNC",
				"twitter": "unchartedUNC"
			},
			"data_twitter": {
				"data": {
					"followers_count": 81173,
					"following_count": 36,
					"tweet_count": 75,
					"listed_count": 1
				}
			},
			"data_telegram": {
				"data": 54127
			}
		}
	]
}